cotton_daisy/__init__.py
cotton_daisy/base.py
cotton_daisy/cli.py
cotton_daisy/templates/alert.html
cotton_daisy/templates/avatar.html
cotton_daisy/templates/avatar_group.html
cotton_daisy/templates/badge.html
cotton_daisy/templates/button.html
cotton_daisy/templates/card.html
cotton_daisy/templates/card_actions.html
cotton_daisy/templates/card_body.html
cotton_daisy/templates/divider.html
cotton_daisy/templates/dropdown.html
cotton_daisy/templates/dropdown_content.html
cotton_daisy/templates/figure.html
cotton_daisy/templates/hero.html
cotton_daisy/templates/kbd.html
cotton_daisy/templates/loading.html
cotton_daisy/templates/menu.html
cotton_daisy/templates/modal.html
cotton_daisy/templates/navbar.html
cotton_daisy/templates/navbar_content.html
cotton_daisy/templates/progress.html
cotton_daisy/templates/skeleton.html
cotton_daisy/templates/step.html
cotton_daisy/templates/steps.html
cotton_daisy/templates/toast.html
cotton_daisy/templates/tooltip.html
cotton_daisy-0.0.17.dist-info/LICENSE
cotton_daisy-0.0.17.dist-info/METADATA
cotton_daisy-0.0.17.dist-info/WHEEL
cotton_daisy-0.0.17.dist-info/entry_points.txt
cotton_daisy-0.0.17.dist-info/RECORD
