Metadata-Version: 2.3
Name: cotton-daisy
Version: 0.0.17
Summary: CLI for generating DaisyUI components for Django-Cotton
License: MIT
Author: Adrian Ciołek
Author-email: ciolek.adrian@protonmail.com
Requires-Python: >=3.12,<4.0
Classifier: License :: OSI Approved :: MIT License
Classifier: Programming Language :: Python :: 3
Classifier: Programming Language :: Python :: 3.12
Classifier: Programming Language :: Python :: 3.13
Requires-Dist: typer (>=0.14.0,<0.15.0)
